easygTTS/__init__.py
easygTTS/_decos.py
easygTTS/easygTTS.py
easygTTS/enums.py
easygTTS/errors.py
easy_gTTS-0.1.1.dist-info/LICENCE
easy_gTTS-0.1.1.dist-info/METADATA
easy_gTTS-0.1.1.dist-info/WHEEL
easy_gTTS-0.1.1.dist-info/top_level.txt
easy_gTTS-0.1.1.dist-info/RECORD
