Metadata-Version: 2.1
Name: easy-gTTS
Version: 0.1.1
Summary: Async interfaces to the easy-gTTS-API
Home-page: https://github.com/regulad/easy-gTTS-py
Author: regulad
Author-email: regulad@outlook.com
License: MIT
Download-URL: https://github.com/regulad/easy-gTTS-py/archive/refs/heads/master.zip
Keywords: async,TTS,text to speech
Platform: UNKNOWN
Classifier: Intended Audience :: Developers
Classifier: License :: OSI Approved :: MIT License
Classifier: Programming Language :: Python :: 3
Classifier: Programming Language :: Python :: 3.6
Classifier: Programming Language :: Python :: 3.7
Classifier: Programming Language :: Python :: 3.8
Classifier: Programming Language :: Python :: 3.9
License-File: LICENCE
Requires-Dist: aiohttp
